django_makemessages_xgettext/__init__.py
django_makemessages_xgettext/admin.py
django_makemessages_xgettext/django17_makemessagesxgettext.py
django_makemessages_xgettext/django18_makemessagesxgettext.py
django_makemessages_xgettext/models.py
django_makemessages_xgettext/tests.py
django_makemessages_xgettext/views.py
django_makemessages_xgettext/management/__init__.py
django_makemessages_xgettext/management/commands/__init__.py
django_makemessages_xgettext/management/commands/makemessagesxgettext.py
django_makemessages_xgettext/migrations/__init__.py
django_makemessages_xgettext-0.1.1.dist-info/DESCRIPTION.rst
django_makemessages_xgettext-0.1.1.dist-info/METADATA
django_makemessages_xgettext-0.1.1.dist-info/RECORD
django_makemessages_xgettext-0.1.1.dist-info/WHEEL
django_makemessages_xgettext-0.1.1.dist-info/metadata.json
django_makemessages_xgettext-0.1.1.dist-info/top_level.txt
