Metadata-Version: 1.1
Name: django-makemessages-xgettext
Version: 0.1.1
Summary: makemessages command that allows for arguments to be passed to xgettext.
Home-page: https://github.com/resulto-admin/django-makemessages-xgettext
Author: Resulto Dev Team
Author-email: dev@resulto.ca
License: New BSD
Keywords: django makemessages xgettext gettext
Platform: UNKNOWN
Classifier: Development Status :: 4 - Beta
Classifier: Intended Audience :: Developers
Classifier: Topic :: Software Development :: Libraries :: Python Modules
Classifier: Topic :: Software Development :: Internationalization
Classifier: License :: OSI Approved :: BSD License
Classifier: Programming Language :: Python :: 2
Classifier: Programming Language :: Python :: 2.7
Classifier: Programming Language :: Python :: 3
Classifier: Programming Language :: Python :: 3.4
